base64c/__init__.py
base64c/base64c.c
base64c/base64c.h
base64c/base64c.pyi
base64c-0.0.5.dist-info/LICENSE
base64c-0.0.5.dist-info/METADATA
base64c-0.0.5.dist-info/WHEEL
base64c-0.0.5.dist-info/RECORD
