Metadata-Version: 2.1
Name: base64c
Version: 0.0.5
Summary: Fast Base64 encoding/decoding with SSE2 and VSX optimizations
Author: obahamonde
Author-email: oscar.bahamonde@indiecloud.co
Requires-Python: >=3.8.0,<4.0
Classifier: Programming Language :: Python :: 3
Classifier: Programming Language :: Python :: 3.8
Classifier: Programming Language :: Python :: 3.9
Classifier: Programming Language :: Python :: 3.10
Classifier: Programming Language :: Python :: 3.11
Classifier: Programming Language :: Python :: 3.12
